{"attributes": {"isStatic": true, "name": "Dimension", "hasWarning": true, "packageName": "qx.bom.element2", "fullName": "qx.bom.element2.Dimension", "type": "class"}, "type": "class", "children": [{"attributes": {"text": "<p>Rewritten support for applying style properties.</p>\n\n<p>Differences to old implementation:</p>\n\n<ul>\n<li>Faster compution</li>\n<li>No special support for scroll bars which not that much</li>\n</ul>"}, "type": "desc"}, {"type": "methods-static", "children": [{"attributes": {"hasError": true, "isStatic": true, "name": "getContentHeight"}, "type": "method", "children": [{"type": "params", "children": [{"attributes": {"name": "elem"}, "type": "param"}]}, {"type": "errors", "children": [{"attributes": {"msg": "Parameter <code>elem</code> is not documented.", "column": 24, "line": 43}, "type": "error"}, {"attributes": {"msg": "Documentation is missing.", "column": 24, "line": 43}, "type": "error"}]}]}, {"attributes": {"hasError": true, "isStatic": true, "name": "getContentWidth"}, "type": "method", "children": [{"type": "params", "children": [{"attributes": {"name": "elem"}, "type": "param"}]}, {"type": "errors", "children": [{"attributes": {"msg": "Parameter <code>elem</code> is not documented.", "column": 23, "line": 33}, "type": "error"}, {"attributes": {"msg": "Documentation is missing.", "column": 23, "line": 33}, "type": "error"}]}]}, {"attributes": {"hasError": true, "isStatic": true, "name": "getHeight"}, "type": "method", "children": [{"type": "params", "children": [{"attributes": {"name": "elem"}, "type": "param"}]}, {"type": "errors", "children": [{"attributes": {"msg": "Parameter <code>elem</code> is not documented.", "column": 17, "line": 57}, "type": "error"}, {"attributes": {"msg": "Documentation is missing.", "column": 17, "line": 57}, "type": "error"}]}]}, {"attributes": {"hasError": true, "isStatic": true, "name": "getWidth"}, "type": "method", "children": [{"type": "params", "children": [{"attributes": {"name": "elem"}, "type": "param"}]}, {"type": "errors", "children": [{"attributes": {"msg": "Parameter <code>elem</code> is not documented.", "column": 16, "line": 53}, "type": "error"}, {"attributes": {"msg": "Documentation is missing.", "column": 16, "line": 53}, "type": "error"}]}]}]}]}